tinuous/__init__.py
tinuous/__main__.py
tinuous/_version.py
tinuous/appveyor.py
tinuous/base.py
tinuous/circleci.py
tinuous/config.py
tinuous/github.py
tinuous/state.py
tinuous/travis.py
tinuous/util.py
tinuous-0.7.0.dist-info/LICENSE
tinuous-0.7.0.dist-info/METADATA
tinuous-0.7.0.dist-info/WHEEL
tinuous-0.7.0.dist-info/entry_points.txt
tinuous-0.7.0.dist-info/top_level.txt
tinuous-0.7.0.dist-info/RECORD
