Metadata-Version: 2.1
Name: tinuous
Version: 0.7.0
Summary: Download build logs from GitHub Actions, Travis, and Appveyor
Home-page: https://github.com/con/tinuous
Author: Center for Open Neuroscience
Author-email: debian@onerussian.com
Maintainer: John T. Wodder II
Maintainer-email: tinuous@varonathe.org
License: MIT
Project-URL: Source Code, https://github.com/con/tinuous
Project-URL: Bug Tracker, https://github.com/con/tinuous/issues
Keywords: Appveyor,GitHub Actions,Travis CI,continuous integration
Classifier: Development Status :: 4 - Beta
Classifier: Programming Language :: Python :: 3 :: Only
Classifier: Programming Language :: Python :: 3
Classifier: Programming Language :: Python :: 3.8
Classifier: Programming Language :: Python :: 3.9
Classifier: Programming Language :: Python :: 3.10
Classifier: Programming Language :: Python :: 3.11
Classifier: Programming Language :: Python :: 3.12
Classifier: Programming Language :: Python :: Implementation :: CPython
Classifier: Programming Language :: Python :: Implementation :: PyPy
Classifier: License :: OSI Approved :: MIT License
Classifier: Intended Audience :: Developers
Classifier: Topic :: System :: Filesystems
Requires-Python: >=3.8
License-File: LICENSE
Requires-Dist: click >=7.0
Requires-Dist: click-loglevel ~=0.2
Requires-Dist: ghtoken ~=0.1
Requires-Dist: in-place ~=1.0
Requires-Dist: pydantic ~=2.0
Requires-Dist: python-dateutil ~=2.7
Requires-Dist: python-dotenv <2.0,>=0.11
Requires-Dist: PyYAML >=5.0
Requires-Dist: requests ~=2.20
Requires-Dist: typing-extensions ; python_version < "3.9"
Provides-Extra: all
Requires-Dist: datalad ~=0.14 ; extra == 'all'
Provides-Extra: datalad
Requires-Dist: datalad ~=0.14 ; extra == 'datalad'
